xhpubs/__init__.py
xhpubs/misc.py
xhpubs-0.0.1.dist-info/LICENSE
xhpubs-0.0.1.dist-info/METADATA
xhpubs-0.0.1.dist-info/WHEEL
xhpubs-0.0.1.dist-info/top_level.txt
xhpubs-0.0.1.dist-info/RECORD
